pr_to_task/__init__.py
pr_to_task/main.py
pr_to_task/models.py
pr_to_task/pr_fetch.py
pr_to_task/prompts.py
pr_to_task/tasks.py
pr_to_task/templates/agents_md.md
pr_to_task/templates/all_tasks_complete.txt
pr_to_task/templates/process_comments.py.j2
pr_to_task/templates/task_complete_confirmation.txt
pr_to_task/templates/task_next_prompt.txt
pr_to_task-0.1.0.dist-info/WHEEL
pr_to_task-0.1.0.dist-info/entry_points.txt
pr_to_task-0.1.0.dist-info/METADATA
pr_to_task-0.1.0.dist-info/RECORD
