Metadata-Version: 2.3
Name: pr_to_task
Version: 0.1.0
Summary: Pull requests to task management
Author: Arthur Souza Rodrigues
Author-email: Arthur Souza Rodrigues <arthrod@gmail.com>
License: MIT License
Requires-Dist: jinja2>=3.1.6
Requires-Dist: requests>=2.32.5
Requires-Dist: typer>=0.20.0
Requires-Dist: typing-extensions>=4.15.0
Requires-Python: >=3.13.7
Project-URL: homepage, https://github.com/arthrod/get-comments-and-hooks#readme
Project-URL: repository, https://github.com/arthrod/get-comments-and-hooks
